fw_logging.py
fw_logging-2.2.0.dist-info/METADATA
fw_logging-2.2.0.dist-info/WHEEL
fw_logging-2.2.0.dist-info/entry_points.txt
fw_logging-2.2.0.dist-info/licenses/LICENSE
fw_logging-2.2.0.dist-info/RECORD
