Metadata-Version: 2.4
Name: fw-logging
Version: 2.2.0
Summary: Logging helper library.
Project-URL: Repository, https://gitlab.com/flywheel-io/tools/lib/fw-logging
Author-email: Flywheel <support@flywheel.io>
License-Expression: MIT
License-File: LICENSE
Keywords: Flywheel,helper,logging
Classifier: Topic :: Software Development :: Libraries :: Python Modules
Requires-Python: <4,>=3.10
Requires-Dist: devtools<1,>=0
Requires-Dist: pydantic-settings<3,>=2.0.2
Requires-Dist: pydantic<3,>=2.1.1
Requires-Dist: pygments<3,>=2.13.0
Requires-Dist: python-dateutil<3,>=2.8.2
Requires-Dist: striprtf<1,>=0
